smarthunter/__init__.py
smarthunter/_base.py
smarthunter/_finder_fallback.py
smarthunter/cli.py
smarthunter/core.py
smarthunter/main.py
smarthunter/registry.py
smarthunter/util.py
smarthunter/decoders/__init__.py
smarthunter/decoders/base32_rs.py
smarthunter/decoders/base64_rs.py
smarthunter/decoders/base85_rs.py
smarthunter/decoders/basexx.py
smarthunter/decoders/braille.py
smarthunter/decoders/cleartext.py
smarthunter/decoders/decimal.py
smarthunter/decoders/hex.py
smarthunter/decoders/morse.py
smarthunter/decoders/octal.py
smarthunter/decoders/url.py
smarthunter/decoders/utf16.py
smarthunter-1.0.2.dist-info/licenses/LICENSE
smarthunter-1.0.2.dist-info/METADATA
smarthunter-1.0.2.dist-info/WHEEL
smarthunter-1.0.2.dist-info/entry_points.txt
smarthunter-1.0.2.dist-info/top_level.txt
smarthunter-1.0.2.dist-info/RECORD
